nonebot_plugin_dst_qq/__init__.py
nonebot_plugin_dst_qq/admin_commands.py
nonebot_plugin_dst_qq/base_api.py
nonebot_plugin_dst_qq/cache_manager.py
nonebot_plugin_dst_qq/cluster_commands.py
nonebot_plugin_dst_qq/cluster_manager.py
nonebot_plugin_dst_qq/config.py
nonebot_plugin_dst_qq/debug_commands.py
nonebot_plugin_dst_qq/item_commands.py
nonebot_plugin_dst_qq/item_data.py
nonebot_plugin_dst_qq/main_menu.py
nonebot_plugin_dst_qq/message_dedup.py
nonebot_plugin_dst_qq/message_utils.py
nonebot_plugin_dst_qq/scheduler.py
nonebot_plugin_dst_qq/server_browser.py
nonebot_plugin_dst_qq/server_browser_commands.py
nonebot_plugin_dst_qq/server_commands.py
nonebot_plugin_dst_qq/simple_cache.py
nonebot_plugin_dst_qq/utils.py
nonebot_plugin_dst_qq/wiki_screenshot.py
nonebot_plugin_dst_qq/assets/menu_background.jpg
nonebot_plugin_dst_qq/database/__init__.py
nonebot_plugin_dst_qq/database/connection.py
nonebot_plugin_dst_qq/database/models.py
nonebot_plugin_dst_qq/plugins/__init__.py
nonebot_plugin_dst_qq/plugins/dmp_advanced.py
nonebot_plugin_dst_qq/plugins/dmp_api.py
nonebot_plugin_dst_qq/plugins/message_bridge.py
nonebot_plugin_dst_qq-0.5.2.dist-info/METADATA
nonebot_plugin_dst_qq-0.5.2.dist-info/WHEEL
nonebot_plugin_dst_qq-0.5.2.dist-info/licenses/LICENSE
nonebot_plugin_dst_qq-0.5.2.dist-info/RECORD
