Metadata-Version: 2.4
Name: nonebot-plugin-dst-qq
Version: 0.5.2
Summary: 🎮 功能丰富的饥荒管理平台 (DMP) QQ 机器人插件，基于 NoneBot2 和 Alconna 构建，提供服务器管理、消息互通、Wiki截图等全方位功能
Project-URL: Homepage, https://github.com/uitok/nonebot-plugin-dst-qq
Project-URL: Repository, https://github.com/uitok/nonebot-plugin-dst-qq
Project-URL: Documentation, https://github.com/uitok/nonebot-plugin-dst-qq#readme
Project-URL: Bug Tracker, https://github.com/uitok/nonebot-plugin-dst-qq/issues
Author-email: uitok <ui_101@qq.com>
License: MIT
License-File: LICENSE
Keywords: aiosqlite,alconna,beautifulsoup4,dmp,don't starve together,dst,htmlrender,message-exchange,nonebot,nonebot2,plugin,qq-bot,server-browser,wiki-screenshot,饥荒
Classifier: Development Status :: 4 - Beta
Classifier: Intended Audience :: Developers
Classifier: License :: OSI Approved :: MIT License
Classifier: Operating System :: OS Independent
Classifier: Programming Language :: Python :: 3
Classifier: Programming Language :: Python :: 3.9
Classifier: Programming Language :: Python :: 3.10
Classifier: Programming Language :: Python :: 3.11
Classifier: Programming Language :: Python :: 3.12
Classifier: Topic :: Communications :: Chat
Classifier: Topic :: Games/Entertainment
Classifier: Topic :: Software Development :: Libraries :: Python Modules
Requires-Python: <4.0,>=3.9
Requires-Dist: aiosqlite>=0.19.0
Requires-Dist: beautifulsoup4>=4.12.0
Requires-Dist: httpx>=0.24.0
Requires-Dist: nonebot-adapter-onebot>=2.4.0
Requires-Dist: nonebot-plugin-alconna>=0.22.0
Requires-Dist: nonebot-plugin-apscheduler>=0.4.0
Requires-Dist: nonebot-plugin-htmlrender>=0.3.0
Requires-Dist: nonebot-plugin-localstore>=0.6.0
Requires-Dist: nonebot-plugin-waiter>=0.3.0
Requires-Dist: nonebot2>=2.4.0
Requires-Dist: pydantic
Provides-Extra: dev
Requires-Dist: black>=23.0.0; extra == 'dev'
Requires-Dist: flake8>=6.0.0; extra == 'dev'
Requires-Dist: isort>=5.12.0; extra == 'dev'
Requires-Dist: mypy>=1.0.0; extra == 'dev'
Requires-Dist: pytest-asyncio>=0.21.0; extra == 'dev'
Requires-Dist: pytest>=7.0.0; extra == 'dev'
